NeoAgent/Chatagent.py
NeoAgent/Knowledge_graph.py
NeoAgent/__init__.py
xxyxx-0.1.0.dist-info/METADATA
xxyxx-0.1.0.dist-info/WHEEL
xxyxx-0.1.0.dist-info/top_level.txt
xxyxx-0.1.0.dist-info/RECORD
